{"100:1":[["n","Ea`diya`t","Edw","عدو","عَٰدِيَٰت","fp","p+det",null,null,null,"act","gen","pcpl",3],["n","DaboH","DbH","ضبح","ضَبْح","m,ind",null,null,null,null,null,"acc"]],"100:2":[["n","muwriya`t","wry","وري","مُورِيَٰت","fp","conj+det",null,"4",null,"act","gen","pcpl",3],["n","qadoH","qdH","قدح","قَدْح","m,ind",null,null,null,null,null,"acc"]],"100:3":[["n","mugiyra`t","gyr","غير","مُغِيرَٰت","fp","conj+det",null,"4",null,"act","gen","pcpl",3],["t","SuboH","SbH","صبح","صُبْح","m,ind",null,null,null,null,null,"acc"]],"100:4":[["v",">avaAru","vwr","ثور","أَثَارُ","3fp","conj","pr:3fp","4","pf",null,null,null,3],["pro",null,null,null,null,"3ms","p",null,null,null,null,null,null,2],["n","naqoE","nqE","نقع","نَقْع","m,ind",null,null,null,null,null,"acc"]],"100:5":[["v","wasaTo","wsT","وسط","وَسَطْ","3fp","conj","pr:3fp",null,"pf",null,null,null,3],["pro",null,null,null,null,"3ms","p",null,null,null,null,null,null,2],["n","jamoE","jmE","جمع","جَمْع","m,ind",null,null,null,null,null,"acc"]],"100:6":[["acc","<in~",null,null,"إِنّ","sp:<in~"],["n","<insa`n","Ans","انس","إِنسَٰن","m","det",null,null,null,null,"acc",null,2],["n","rab~","rbb","ربب","رَبّ","m","p","pr:3ms",null,null,null,"gen",null,3],["n","kanuwd","knd","كند","كَنُود","ms,ind","emp",null,null,null,null,"nom",null,2]],"100:7":[["acc","<in~",null,null,"إِنّ","sp:<in~","conj","pr:3ms",null,null,null,null,null,3],["p","EalaY`",null,null,"عَلَىٰ"],["dem","*a`lik",null,null,"ذَٰلِك","ms"],["n","$ahiyd","$hd","ٕهد","َٕهِيد","ms,ind","emp",null,null,null,null,"nom",null,2]],"100:8":[["acc","<in~",null,null,"إِنّ","sp:<in~","conj","pr:3ms",null,null,null,null,null,3],["n","Hub~","Hbb","حبب","حُبّ","m","p",null,null,null,null,"gen",null,2],["n","xayor","xyr","خير","خَيْر","ms","det",null,null,null,null,"gen",null,2],["n","$adiyd","$dd","ٕدد","َٕدِيد","ms,ind","emp",null,null,null,null,"nom",null,2]],"100:9":[["neg","laA",null,null,"لَا",null,"intg+sup",null,null,null,null,null,null,3],["v","Ealima","Elm","علم","عَلِمَ","3ms",null,null,null,"im"],["t","<i*aA",null,null,"إِذَا"],["v","buEovira","bEvr","بعثر","بُعْثِرَ","3ms",null,null,null,"pf","pas"],["rel","maA",null,null,"مَا"],["p","fiY",null,null,"فِى"],["n","qabor","qbr","قبر","قَبْر","mp","det",null,null,null,null,"gen",null,2]],"100:10":[["v","HuS~ila","HSl","حصل","حُصِّلَ","3ms","conj",null,"2","pf","pas",null,null,2],["rel","maA",null,null,"مَا"],["p","fiY",null,null,"فِى"],["n","Sador","Sdr","صدر","صَدْر","mp","det",null,null,null,null,"gen",null,2]],"100:11":[["acc","<in~",null,null,"إِنّ","sp:<in~"],["n","rab~","rbb","ربب","رَبّ","m",null,"pr:3mp",null,null,null,"acc",null,2],["pro",null,null,null,null,"3mp","p",null,null,null,null,null,null,2],["t","yawoma}i*",null,null,"يَوْمَئِذ"],["n","xabiyr","xbr","خبر","خَبِير","ms,ind","emp",null,null,null,null,"nom",null,2]]}