{"93:1":[["n","DuHFY","DHw","ضحو","ضُحًى","m","p+det",null,null,null,null,"gen",null,3]],"93:2":[["n","layol","lyl","ليل","لَيْل","m","conj+det",null,null,null,null,"gen",null,3],["t","<i*aA",null,null,"إِذَا"],["v","sajaY`","sjw","سجو","سَجَىٰ","3ms",null,null,null,"pf"]],"93:3":[["neg","maA",null,null,"مَا"],["v","wad~aEa","wdE","ودع","وَدَّعَ","3ms",null,"pr:2ms","2","pf",null,null,null,2],["n","rab~","rbb","ربب","رَبّ","m",null,"pr:2ms",null,null,null,"nom",null,2],["neg","maA",null,null,"مَا",null,"conj",null,null,null,null,null,null,2],["v","qalaY`","qly","قلي","قَلَىٰ","3ms",null,null,null,"pf"]],"93:4":[["n","A^xir","Axr","اخر","آخِر","fs","rem+emp+det",null,null,null,null,"nom",null,4],["n","xayor","xyr","خير","خَيْر","ms,ind",null,null,null,null,null,"nom"],["pro",null,null,null,null,"2ms","p",null,null,null,null,null,null,2],["p","min",null,null,"مِن"],["n",">aw~al","Awl","اول","أَوَّل","f","det",null,null,null,null,"gen",null,2]],"93:5":[["fut","sawof",null,null,"سَوْف",null,"rem+emp",null,null,null,null,null,null,3],["v",">aEoTaY`","ETw","عطو","أَعْطَىٰ","3ms",null,"pr:2ms","4","im",null,null,null,2],["n","rab~","rbb","ربب","رَبّ","m",null,"pr:2ms",null,null,null,"nom",null,2],["v","r~aDiYa","rDw","رضو","رَّضِىَ","2ms","conj",null,null,"im",null,null,null,2]],"93:6":[["neg","lam",null,null,"لَم",null,"intg",null,null,null,null,null,null,2],["v","wajada","wjd","وجد","وَجَدَ","3ms,mood:jus",null,"pr:2ms",null,"im",null,null,null,2],["n","yatiym","ytm","يتم","يَتِيم","ms,ind",null,null,null,null,null,"acc"],["v","'aAwaY`^","Awy","اوي","ءَاوَىٰٓ","3ms","conj",null,"4","pf",null,null,null,2]],"93:7":[["v","wajada","wjd","وجد","وَجَدَ","3ms","conj","pr:2ms",null,"pf",null,null,null,3],["n","DaA^l~","Dll","ضلل","ضَآلّ","m,ind",null,null,null,null,"act","acc","pcpl"],["v","hadaY","hdy","هدي","هَدَى","3ms","conj",null,null,"pf",null,null,null,2]],"93:8":[["v","wajada","wjd","وجد","وَجَدَ","3ms","conj","pr:2ms",null,"pf",null,null,null,3],["n","EaA^}il","Eyl","عيل","عَآئِل","m,ind",null,null,null,null,"act","acc","pcpl"],["v",">agonaY`","gny","غني","أَغْنَىٰ","3ms","conj",null,null,"pf",null,null,null,2]],"93:9":[["exl",">am~aA",null,null,"أَمَّا",null,"rem",null,null,null,null,null,null,2],["n","yatiym","ytm","يتم","يَتِيم","ms","det",null,null,null,null,"acc",null,2],["pro","laA",null,null,"لَا",null,"conj",null,null,null,null,null,null,2],["v","taqoharo","qhr","قهر","تَقْهَرْ","2ms,mood:jus",null,null,null,"im"]],"93:10":[["exl",">am~aA",null,null,"أَمَّا",null,"conj",null,null,null,null,null,null,2],["n","saA^}il","sAl","سال","سَآئِل","m","det",null,null,null,"act","acc","pcpl",2],["pro","laA",null,null,"لَا",null,"conj",null,null,null,null,null,null,2],["v","tanoharo","nhr","نهر","تَنْهَرْ","2ms,mood:jus",null,null,null,"im"]],"93:11":[["exl",">am~aA",null,null,"أَمَّا",null,"conj",null,null,null,null,null,null,2],["n","niEomap","nEm","نعم","نِعْمَة","f","p",null,null,null,null,"gen",null,2],["n","rab~","rbb","ربب","رَبّ","m",null,"pr:2ms",null,null,null,"gen",null,2],["v","tuHad~ivu","Hdv","حدث","تُحَدِّثُ","2ms","rem",null,"2","iv",null,null,null,2]]}